silence/__init__.py
silence/auth/__init__.py
silence/auth/tokens.py
silence/cli/__init__.py
silence/cli/manager.py
silence/cli/template_downloader.py
silence/cli/commands/__init__.py
silence/cli/commands/createapi.py
silence/cli/commands/createdb.py
silence/cli/commands/createtests.py
silence/cli/commands/list_templates.py
silence/cli/commands/new.py
silence/cli/commands/run.py
silence/db/__init__.py
silence/db/connector.py
silence/db/dal.py
silence/db/populate.py
silence/decorators/__init__.py
silence/decorators/db_call.py
silence/exceptions/__init__.py
silence/logging/__init__.py
silence/logging/default_formatter.py
silence/logging/default_logger.py
silence/logging/flask_filter.py
silence/logging/handler.py
silence/logging/utils.py
silence/server/__init__.py
silence/server/api_summary.py
silence/server/default_endpoints.py
silence/server/endpoint.py
silence/server/endpoint_creator.py
silence/server/endpoint_loader.py
silence/server/manager.py
silence/server/test_creator.py
silence/settings/__init__.py
silence/settings/default_settings.py
silence/sql/__init__.py
silence/sql/builder.py
silence/sql/converter.py
silence/sql/tables.py
silence/utils/__init__.py
silence/utils/check_update.py
silence/utils/min_type.py
silence/utils/silence_json_encoder.py
Silence-2.2.0.dist-info/LICENSE
Silence-2.2.0.dist-info/METADATA
Silence-2.2.0.dist-info/WHEEL
Silence-2.2.0.dist-info/entry_points.txt
Silence-2.2.0.dist-info/top_level.txt
Silence-2.2.0.dist-info/RECORD
