Metadata-Version: 2.1
Name: Silence
Version: 2.2.0
Summary: An educational API+Web framework.
Home-page: http://github.com/DEAL-US/Silence
Author: Agustín Borrego
Author-email: borrego@us.es
Maintainer: Miguel Bermudo
Maintainer-email: mbermudo@us.es
License: MIT
Requires-Python: ~=3.8
License-File: LICENSE
Requires-Dist: colorama ~=0.4.4
Requires-Dist: cryptography ~=36.0.2
Requires-Dist: Flask-Cors ==3.0.10
Requires-Dist: Flask ==2.0.3
Requires-Dist: itsdangerous ~=2.0.1
Requires-Dist: PyMySQL ~=1.0.2
Requires-Dist: pypika ==0.48.9
Requires-Dist: requests ~=2.27.1
Requires-Dist: Werkzeug ~=2.0.3
